roh_ytd/__init__.py
roh_ytd/downloader.py
tests/__init__.py
tests/test_downloader.py
roh_ytd-2.0.0.dist-info/LICENSE
roh_ytd-2.0.0.dist-info/METADATA
roh_ytd-2.0.0.dist-info/WHEEL
roh_ytd-2.0.0.dist-info/entry_points.txt
roh_ytd-2.0.0.dist-info/top_level.txt
roh_ytd-2.0.0.dist-info/RECORD
