Metadata-Version: 2.1
Name: roh-ytd
Version: 2.0.0
Summary: A Python package for downloading YouTube videos and audio in various formats with a graphical user interface.
Author: Rohan Kumar Bhoi
Author-email: me.rohanbhoi@gmail.com
License: MIT
Classifier: Programming Language :: Python :: 3
Classifier: License :: OSI Approved :: MIT License
Classifier: Operating System :: OS Independent
Requires-Python: >=3.6
License-File: LICENSE
Requires-Dist: yt-dlp
Requires-Dist: ttkthemes
